{"stat.killEntity.Sheep":6,"stat.useItem.3":1565,"stat.mineBlock.37":9,"stat.useItem.65":15,"stat.craftItem.155":13,"stat.useItem.48":4,"stat.mineBlock.114":2,"stat.mineBlock.24":179,"achievement.openInventory":2227,"stat.damageDealt":12685,"stat.mineBlock.31":1230,"stat.useItem.50":228,"stat.breakItem.291":2,"stat.mineBlock.88":27,"stat.mineBlock.107":2,"stat.killEntity.Cow":27,"stat.mineBlock.153":155,"stat.craftItem.50":448,"stat.craftItem.45":2,"stat.craftItem.345":1,"stat.useItem.351":32,"achievement.exploreAllBiomes":{"value":0,"progress":["Canyon","Lavender Fields","Undergarden","rwg_riverIce","rwg_hotPlains","Cherry Blossom Grove","Seasonal Forest","Sacred Springs","rwg_coldForest","rwg_snowForest","Tundra","rwg_temperateForest","Boneyard","Corrupted Sands","Phantasmagoric Inferno","Visceral Heap","rwg_hotDesert","Woodland","Grove","rwg_snowDesert","Highland","rwg_hotForest","Garden","Maple Woods","rwg_riverTemperate","Hell","Snowy Coniferous Forest","rwg_oasis","rwg_riverOasis","Prairie","rwg_riverWet","rwg_riverCold","rwg_riverHot"]},"stat.useItem.112":70,"stat.useItem.324":1,"stat.craftItem.89":1,"stat.useItem.24":1,"stat.craftItem.266":63,"stat.mineBlock.54":14,"stat.mineBlock.49":66,"stat.mineBlock.1":15,"tconstruct.proTinkerer":17,"stat.mineBlock.73":22,"stat.useItem.259":1,"stat.useItem.49":10,"stat.useItem.5":5,"stat.fallOneCm":71877,"stat.flyOneCm":1020381,"tconstruct.tinkerer":34,"stat.mineBlock.61":8,"stat.damageTaken":7257,"stat.useItem.4":1,"stat.useItem.355":14,"tconstruct.pattern":2,"stat.mineBlock.161":10,"stat.mineBlock.162":362,"stat.mineBlock.21":120,"stat.mineBlock.39":6,"stat.mineBlock.38":23,"stat.craftItem.33":34,"stat.mineBlock.82":115,"stat.craftItem.65":12,"achievement.buildWorkBench":4,"stat.useItem.38":8,"stat.mineBlock.86":6,"stat.craftItem.404":8,"stat.craftItem.82":8,"stat.craftItem.259":1,"stat.craftItem.5":1431,"stat.craftItem.58":4,"stat.mineBlock.89":25,"stat.climbOneCm":35542,"stat.craftItem.339":9,"stat.craftItem.291":2,"stat.breakItem.299":1,"stat.craftItem.336":41,"stat.useItem.87":478,"stat.drop":148,"stat.craftItem.263":154,"stat.useItem.291":264,"stat.craftItem.324":1,"stat.mineBlock.14":29,"stat.useItem.175":2,"stat.craftItem.69":1,"stat.useItem.392":4,"stat.breakItem.301":1,"tconstruct.enemySlayer":116,"stat.killEntity.Wolf":1,"stat.mineBlock.66":28,"stat.mineBlock.65":11,"stat.breakItem.300":1,"stat.mineBlock.12":163,"tconstruct.smelteryMaker":4,"stat.killEntity.Creeper":1,"stat.mineBlock.58":3,"stat.mineBlock.15":133,"stat.craftItem.70":1,"stat.killEntity.Enderman":1,"stat.leaveGame":59,"stat.useItem.6":34,"stat.useItem.295":123,"stat.useItem.61":9,"stat.useItem.85":40,"stat.craftItem.126":66,"stat.boatOneCm":940300,"stat.mineBlock.56":19,"stat.useItem.107":2,"stat.mineBlock.6":3,"stat.mineBlock.18":307,"tconstruct.preparedFight":11,"achievement.buildHoe":3,"stat.craftItem.41":7,"achievement.mineWood":1053,"stat.useItem.267":366,"stat.mineBlock.17":273,"stat.useItem.159":150,"stat.mineBlock.48":248,"stat.useItem.17":14,"stat.mineBlock.87":904,"stat.craftItem.85":42,"stat.killEntity.LavaSlime":10,"stat.mineBlock.79":273,"stat.mineBlock.127":21,"stat.craftItem.20":40,"stat.mineBlock.13":317,"stat.playOneMinute":3286160,"stat.useItem.37":1,"stat.diveOneCm":68713,"stat.useItem.391":10,"stat.mineBlock.103":4,"stat.useItem.54":30,"stat.killEntity.Spider":17,"stat.craftItem.22":80,"stat.mineBlock.112":160,"stat.craftItem.1":5,"stat.animalsBred":32,"stat.mineBlock.47":3,"tconstruct.beginner":10,"stat.useItem.58":2,"stat.swimOneCm":128343,"stat.craftItem.280":876,"stat.killEntity.Skeleton":6,"stat.walkOneCm":14633899,"stat.craftItem.380":3,"stat.craftItem.152":7,"stat.killEntity.Silverfish":23,"stat.craftItem.325":2,"stat.breakItem.298":1,"stat.jump":7740,"stat.craftItem.420":2,"stat.useItem.13":23,"stat.mineBlock.81":9,"stat.useItem.12":5,"stat.craftItem.265":144,"stat.craftItem.61":2,"stat.mineBlock.16":6,"stat.craftItem.171":6,"stat.craftItem.44":6,"stat.deaths":2,"stat.mineBlock.3":3587,"stat.blockChiseled":9,"stat.mobKills":219,"stat.mineBlock.159":541,"stat.killEntity.Zombie":4,"stat.craftItem.330":1,"stat.craftItem.54":86,"stat.mineBlock.50":44,"stat.killEntity.Blaze":9,"stat.mineBlock.85":40,"stat.mineBlock.4":261,"stat.craftItem.76":24,"stat.mineBlock.5":5,"stat.mineBlock.129":9,"stat.craftItem.331":18,"stat.mineBlock.175":11,"stat.craftItem.107":2,"stat.craftItem.172":8}